CHANGES.txt
CONTRIBUTORS.txt
README.md
README.txt
setup.cfg
setup.py
cs/__init__.py
cs.seopack.egg-info/PKG-INFO
cs.seopack.egg-info/SOURCES.txt
cs.seopack.egg-info/dependency_links.txt
cs.seopack.egg-info/entry_points.txt
cs.seopack.egg-info/namespace_packages.txt
cs.seopack.egg-info/not-zip-safe
cs.seopack.egg-info/requires.txt
cs.seopack.egg-info/top_level.txt
cs/seopack/__init__.py
cs/seopack/batch.pt
cs/seopack/batch.py
cs/seopack/canonical.pt
cs/seopack/canonical.py
cs/seopack/configure.zcml
cs/seopack/noindex.pt
cs/seopack/noindex.py
cs/seopack/overrides/Products.CMFPlone.skins.plone_templates.batch_macros.pt
docs/HISTORY.txt
docs/INSTALL.txt
docs/LICENSE.GPL
docs/LICENSE.txt