Metadata-Version: 1.1
Name: cs.seopack
Version: 1.1
Summary: Some viewlets to do SEO work in Plone sites
Home-page: http://github.com/codesyntax/cs.seopack
Author: Mikel Larreategi
Author-email: mlarreategi@codesyntax.com
License: GPL
Keywords: plone seo
Platform: UNKNOWN
Classifier: Framework :: Plone
Classifier: Programming Language :: Python
